algs/__init__.py
algs/ais.py
algs/apriori.py
algs/data.py
algs/fp_tree.py
algs/gar.py
algs/gar_plus.py
algs/hash_tree.py
algs/hclique.py
algs/models.py
algs/quantitative.py
algs/rule_gen.py
algs/util.py
algs/datasets/agaricus-lepiota.data
algs/datasets/store_data.csv
rule_mining_algs-0.1.1.dist-info/LICENSE
rule_mining_algs-0.1.1.dist-info/METADATA
rule_mining_algs-0.1.1.dist-info/WHEEL
rule_mining_algs-0.1.1.dist-info/top_level.txt
rule_mining_algs-0.1.1.dist-info/RECORD
