Metadata-Version: 2.1
Name: rule-mining-algs
Version: 0.1.1
Summary: The package contains a few selected association rule mining algorithms.
Author-email: Josef Würf <sepp2357@yahoo.de>
License: MIT License
Project-URL: repository, https://github.com/JosWrf/rule_mining_algs
Keywords: Association Rule Mining
Classifier: Programming Language :: Python :: 3
Requires-Python: >=3.7
License-File: LICENSE
Requires-Dist: mlxtend (>=0.21.0)
Requires-Dist: numpy (>=1.20.0)
Requires-Dist: pandas (>=1.3.0)
Requires-Dist: scikit-learn (>=1.1.0)
